made_ai_dungeon/__init__.py
made_ai_dungeon/data/__init__.py
made_ai_dungeon/data/make_dataset.py
made_ai_dungeon/features/__init__.py
made_ai_dungeon/features/build_features.py
made_ai_dungeon/models/__init__.py
made_ai_dungeon/models/generator_stub.py
made_ai_dungeon/models/gpt2generator.py
made_ai_dungeon/models/hugginface_generator.py
made_ai_dungeon/models/predict_model.py
made_ai_dungeon/models/rest_api_generator.py
made_ai_dungeon/models/train_model.py
made_ai_dungeon/process_text/__init__.py
made_ai_dungeon/process_text/gpt_text_post_processing.py
made_ai_dungeon/story_manager/__init__.py
made_ai_dungeon/story_manager/story_manager.py
made_ai_dungeon/story_manager/text_generator.py
made_ai_dungeon/visualization/__init__.py
made_ai_dungeon/visualization/visualize.py
models/__init__.py
made_ai_dungeon-0.0.4.dist-info/LICENSE
made_ai_dungeon-0.0.4.dist-info/METADATA
made_ai_dungeon-0.0.4.dist-info/WHEEL
made_ai_dungeon-0.0.4.dist-info/top_level.txt
made_ai_dungeon-0.0.4.dist-info/RECORD
