Metadata-Version: 2.1
Name: made-ai-dungeon
Version: 0.0.4
Summary: MADE graduation project
Home-page: UNKNOWN
Author: akoshel
License: UNKNOWN
Platform: UNKNOWN
License-File: LICENSE
